IN3160-20/oblig2/fulladder.vhd

library IEEE;
	use IEEE.STD_LOGIC_1164.all;

entity fulladder is
	port(
		a, b	: in std_logic;
		cin	: in std_logic;
		cout	: out std_logic;
		s	: out std_logic
	);
end entity fulladder;

architecture dataflow of fulladder is
begin
	s <= (a xor b) xor cin;
	cout <= (a and b) or (cin and (a xor b));
end architecture dataflow;

IN2060/oblig2/tb_fulladder.vhd
library IEEE;
	use IEEE.STD_LOGIC_1164.all;
entity tb_fulladder is
end entity tb_fulladder;

architecture behavioral of tb_fulladder is
	component fulladder is
		port(
			a, b	: in std_logic;
			cin	: in std_logic;
			s 	: out std_logic;
			cout	: out std_logic
		);
	end component;

	signal tb_a, tb_b, tb_cin	: std_logic := '0';
	signal tb_s, tb_cout 		: std_logic;

begin 
	DUT: fulladder
	port map(
		a	=> tb_a,
		b 	=> tb_b,
		cin 	=> tb_cin,
		s	=> tb_s,
		cout	=> tb_cout
	);

	process begin
		wait for 10 ns;
		tb_a 	<= '0';
		tb_b 	<= '0';
		tb_cin 	<= '0';

		wait for 10 ns;
		tb_a 	<= '0';
		tb_b 	<= '0';
		tb_cin 	<= '1';

		wait for 10 ns;
		tb_a 	<= '0';
		tb_b 	<= '1';
		tb_cin 	<= '0';

		wait for 10 ns;
		tb_a 	<= '0';
		tb_b 	<= '1';
		tb_cin 	<= '1';

		wait for 10 ns;
		tb_a 	<= '1';
		tb_b 	<= '0';
		tb_cin 	<= '0';

		wait for 10 ns;
		tb_a 	<= '1';
		tb_b 	<= '0';
		tb_cin 	<= '1';

		wait for 10 ns;
		tb_a 	<= '1';
		tb_b 	<= '1';
		tb_cin 	<= '0';

		wait for 10 ns;
		tb_a 	<= '1';
		tb_b 	<= '1';
		tb_cin 	<= '1';

		wait for 10 ns;
		report("Ferdig") severity note;
		std.env.stop;
	end process;

end architecture behavioral;

IN3160-20/oblig2/fulladdertest.vcd
$date
	Sat Sep 26 21:28:37 2020
$end
$version
	QuestaSim Version 2019.4
$end
$timescale
	1fs
$end
$scope module tb_fulladder $end
$scope module DUT $end
$var wire 1 ! a $end
$var wire 1 " b $end
$var wire 1 # cout $end
$var wire 1 $ cin $end
$var wire 1 % s $end
$upscope $end
$upscope $end
$enddefinitions $end
#0
0!
0"
0$
0#
0%
0%
0#
#20000000
1$
1%
#30000000
0$
1"
#40000000
1$
1#
0%
#50000000
0$
0"
1!
0#
1%
#60000000
1$
1#
0%
#70000000
0$
1"
#80000000
1$
1%
